[
  {
    "titulo": "Agenda dos Blocos de Rua do Rio de Janeiro em 2026",
    "resumo": "A Agenda mais completa do carnaval de rua do Rio de Janeiro em 2026, todos os blocos de rua, oficiais e não oficiais, ensaios e festas",
    "url": "https://diariodorio.com/agenda/",
    "fonte": "diariodorio",
    "imagem_url": "data:image/svg+xml,%3Csvg%20xmlns='http://www.w3.org/2000/svg'%20width='696'%20height='515'%20viewBox='0%200%20696%20515'%3E%3C/svg%3E",
    "publicado_em": "2026-02-13T18:01:59.931Z",
    "coletado_em": "2026-02-13T18:01:59.932Z",
    "tags": [],
    "is_alerta": false
  }
]